[
  {
    "Id": "565838",
    "ThreadId": "245950",
    "Html": "\r\n<p>Awesome learning tool. The Documentation .pdf is poetry and should be the benchmark for walk thrus. But what app (these days) exist without Unit Tests? It doesn't seem possible that the team who poured so much work into providing such a creature wouldn't\r\n have employed Unit Tests as they built it. Why not make that work public?<br>\r\n<br>\r\nthx</p>\r\n",
    "PostedDate": "2011-02-14T05:58:35.18-08:00",
    "UserRole": null,
    "MarkedAsAnswerDate": null
  }
]